README.md
setup.cfg
setup.py
perimeterx/__init__.py
perimeterx/middleware.py
perimeterx/px_activities_client.py
perimeterx/px_api.py
perimeterx/px_blocker.py
perimeterx/px_config.py
perimeterx/px_constants.py
perimeterx/px_context.py
perimeterx/px_cookie.py
perimeterx/px_cookie_v1.py
perimeterx/px_cookie_v3.py
perimeterx/px_cookie_validator.py
perimeterx/px_data_enrichment_cookie.py
perimeterx/px_enc_utils.py
perimeterx/px_httpc.py
perimeterx/px_logger.py
perimeterx/px_original_token_validator.py
perimeterx/px_proxy.py
perimeterx/px_request_verifier.py
perimeterx/px_template.py
perimeterx/px_testing_mode_handler.py
perimeterx/px_utils.py
perimeterx/templates/block_template.mustache
perimeterx/templates/ratelimit.mustache
perimeterx_python_3_wsgi.egg-info/PKG-INFO
perimeterx_python_3_wsgi.egg-info/SOURCES.txt
perimeterx_python_3_wsgi.egg-info/dependency_links.txt
perimeterx_python_3_wsgi.egg-info/requires.txt
perimeterx_python_3_wsgi.egg-info/top_level.txt
test/test_px_activities_client.py
test/test_px_api.py
test/test_px_blocker.py
test/test_px_config.py
test/test_px_context.py
test/test_px_cookie.py
test/test_px_cookie_validator.py
test/test_px_data_enrichment_cookie.py
test/test_px_httpc.py
test/test_px_original_token_validator.py
test/test_px_proxy.py
test/test_px_request_validator.py
test/test_px_utils.py