Metadata-Version: 1.1
Name: perimeterx-python-3-wsgi
Version: 1.0.1
Summary: PerimeterX Python 3 WSGI middleware
Home-page: https://github.com/PerimeterX/perimeterx-python-3-wsgi
Author: Johnny Tordgeman
Author-email: johnny@perimeterx.com
License: MIT
Download-URL: https://github.com/PerimeterX/perimeterx-python-3-wsgi/tarball/v1.0.1
Platform: UNKNOWN
Classifier: Intended Audience :: Developers
Classifier: Programming Language :: Python :: 3.7
